Workbook

Sheet Read me
B1: Second Pass: the Excel edition
B2: Version 1.0, 13 September 2026. Built by Khaled Alkurd.
B3: https://fiscalpatriots.github.io/beat-the-machine/
B5: What this workbook does
B6: It runs the two checks a spreadsheet can run honestly. The threshold check recomputes the change and the percent on every account from the two balances and says which lines owe commentary under the rule on the Settings sheet. The silence check names every account that owes commentary and carries no sentence in the memo. The reviewer log is the evidence the close file keeps.
B7: It does not read your sentences. Nothing in here parses English, so arithmetic and direction are checked by you: the Memo sheet puts the figure the sentence states beside the figure the ledger carries, and beside the direction the balance actually moved, and you decide whether they agree. The comparison is arithmetic the workbook does; the reading is yours.
B8: Judgment stays where the protocol puts it. Whether a driver is supported by a document on file, and whether it belongs to the period the sentence covers, are questions for the reviewer and they never appear here as a verdict.
B10: How to use it, five steps
B11: 1. Open Settings and set the dollar floor, the percent floor, the rule, the close period and the memo version for the close you are working.
B12: 2. Replace the fourteen Halyard rows on Ledger with your own accounts, prior and current balances. Thirty blank rows below carry the same formulas. Change, percent and the two threshold legs compute themselves.
B13: 3. Paste the memo on the Memo sheet, one sentence per row. Pick the account from the dropdown, type the figure the sentence states, pick which ledger figure it claims to be, and pick the direction the sentence states. Percent figures go in as points, so 7.1 for 7.1 percent.
B14: 4. Read the Result column. FAIL means a figure or a direction does not agree with the ledger and the sentence goes back to the preparer. INFO means the account owes no commentary, and the sentence is still checked because a sentence that owes nothing can still say something false. REVIEW means the mechanical checks cleared it and it is yours to judge. Then read Silence, which lists every account that owes an explanation and has none written.
... B27: PROTOCOL.md in this repository is the one page a reviewer works from, EVIDENCE-LOG-TEMPLATE.csv is the log, and the browser version of the same checks is at https://fiscalpatriots.github.io/beat-the-machine/checker.html.

Sheet Ledger
A1: Account | B1: Name | C1: Prior | D1: Current | E1: Change | F1: Percent | G1: Clears dollar leg | H1: Clears percent leg | I1: Owes commentary
A2: 4000 | B2: Product revenue, distribution | C2: 5240000 | D2: 5612000 | E2: =IF(OR($C2="",$D2=""),"",$D2-$C2) | F2: =IF(OR($C2="",$D2="",$C2=0),"",($D2-$C2)/ABS($C2)) | G2: =IF($E2="","",IF(ABS($E2)>Settings!$B$2,"yes","no")) | H2: =IF($F2="","",IF(ABS($F2)>=Settings!$B$3/100,"yes","no")) | I2: =IF($E2="","",IF(LOWER(Settings!$B$4)="both",IF(AND($G2="yes",$H2="yes"),"yes","no"),IF(OR($G2="yes",$H2="yes"),"yes","no")))
A3: 4100 | B3: Service revenue, equipment maintenance | C3: 812000 | D3: 1041000 | E3: =IF(OR($C3="",$D3=""),"",$D3-$C3) | F3: =IF(OR($C3="",$D3="",$C3=0),"",($D3-$C3)/ABS($C3)) | G3: =IF($E3="","",IF(ABS($E3)>Settings!$B$2,"yes","no")) | H3: =IF($F3="","",IF(ABS($F3)>=Settings!$B$3/100,"yes","no")) | I3: =IF($E3="","",IF(LOWER(Settings!$B$4)="both",IF(AND($G3="yes",$H3="yes"),"yes","no"),IF(OR($G3="yes",$H3="yes"),"yes","no")))
A4: 4200 | B4: Freight billed to customers | C4: 186000 | D4: 121000 | E4: =IF(OR($C4="",$D4=""),"",$D4-$C4) | F4: =IF(OR($C4="",$D4="",$C4=0),"",($D4-$C4)/ABS($C4)) | G4: =IF($E4="","",IF(ABS($E4)>Settings!$B$2,"yes","no")) | H4: =IF($F4="","",IF(ABS($F4)>=Settings!$B$3/100,"yes","no")) | I4: =IF($E4="","",IF(LOWER(Settings!$B$4)="both",IF(AND($G4="yes",$H4="yes"),"yes","no"),IF(OR($G4="yes",$H4="yes"),"yes","no")))
A5: 5000 | B5: Cost of product sold | C5: 3930000 | D5: 4278000 | E5: =IF(OR($C5="",$D5=""),"",$D5-$C5) | F5: =IF(OR($C5="",$D5="",$C5=0),"",($D5-$C5)/ABS($C5)) | G5: =IF($E5="","",IF(ABS($E5)>Settings!$B$2,"yes","no")) | H5: =IF($F5="","",IF(ABS($F5)>=Settings!$B$3/100,"yes","no")) | I5: =IF($E5="","",IF(LOWER(Settings!$B$4)="both",IF(AND($G5="yes",$H5="yes"),"yes","no"),IF(OR($G5="yes",$H5="yes"),"yes","no")))
A6: 5100 | B6: Inbound freight | C6: 214000 | D6: 287800 | E6: =IF(OR($C6="",$D6=""),"",$D6-$C6) | F6: =IF(OR($C6="",$D6="",$C6=0),"",($D6-$C6)/ABS($C6)) | G6: =IF($E6="","",IF(ABS($E6)>Settings!$B$2,"yes","no")) | H6: =IF($F6="","",IF(ABS($F6)>=Settings!$B$3/100,"yes","no")) | I6: =IF($E6="","",IF(LOWER(Settings!$B$4)="both",IF(AND($G6="yes",$H6="yes"),"yes","no"),IF(OR($G6="yes",$H6="yes"),"yes","no")))
A7: 6000 | B7: Warehouse wages | C7: 630000 | D7: 702500 | E7: =IF(OR($C7="",$D7=""),"",$D7-$C7) | F7: =IF(OR($C7="",$D7="",$C7=0),"",($D7-$C7)/ABS($C7)) | G7: =IF($E7="","",IF(ABS($E7)>Settings!$B$2,"yes","no")) | H7: =IF($F7="","",IF(ABS($F7)>=Settings!$B$3/100,"yes","no")) | I7: =IF($E7="","",IF(LOWER(Settings!$B$4)="both",IF(AND($G7="yes",$H7="yes"),"yes","no"),IF(OR($G7="yes",$H7="yes"),"yes","no")))
A8: 6100 | B8: Fleet fuel | C8: 96400 | D8: 91200 | E8: =IF(OR($C8="",$D8=""),"",$D8-$C8) | F8: =IF(OR($C8="",$D8="",$C8=0),"",($D8-$C8)/ABS($C8)) | G8: =IF($E8="","",IF(ABS($E8)>Settings!$B$2,"yes","no")) | H8: =IF($F8="","",IF(ABS($F8)>=Settings!$B$3/100,"yes","no")) | I8: =IF($E8="","",IF(LOWER(Settings!$B$4)="both",IF(AND($G8="yes",$H8="yes"),"yes","no"),IF(OR($G8="yes",$H8="yes"),"yes","no")))
A9: 6200 | B9: Repairs and maintenance, depots | C9: 41000 | D9: 118600 | E9: =IF(OR($C9="",$D9=""),"",$D9-$C9) | F9: =IF(OR($C9="",$D9="",$C9=0),"",($D9-$C9)/ABS($C9)) | G9: =IF($E9="","",IF(ABS($E9)>Settings!$B$2,"yes","no")) | H9: =IF($F9="","",IF(ABS($F9)>=Settings!$B$3/100,"yes","no")) | I9: =IF($E9="","",IF(LOWER(Settings!$B$4)="both",IF(AND($G9="yes",$H9="yes"),"yes","no"),IF(OR($G9="yes",$H9="yes"),"yes","no")))
A10: 6300 | B10: Software subscriptions | C10: 28500 | D10: 30100 | E10: =IF(OR($C10="",$D10=""),"",$D10-$C10) | F10: =IF(OR($C10="",$D10="",$C10=0),"",($D10-$C10)/ABS($C10)) | G10: =IF($E10="","",IF(ABS($E10)>Settings!$B$2,"yes","no")) | H10: =IF($F10="","",IF(ABS($F10)>=Settings!$B$3/100,"yes","no")) | I10: =IF($E10="","",IF(LOWER(Settings!$B$4)="both",IF(AND($G10="yes",$H10="yes"),"yes","no"),IF(OR($G10="yes",$H10="yes"),"yes","no")))
A11: 6400 | B11: Bad debt expense | C11: 15000 | D11: 62000 | E11: =IF(OR($C11="",$D11=""),"",$D11-$C11) | F11: =IF(OR($C11="",$D11="",$C11=0),"",($D11-$C11)/ABS($C11)) | G11: =IF($E11="","",IF(ABS($E11)>Settings!$B$2,"yes","no")) | H11: =IF($F11="","",IF(ABS($F11)>=Settings!$B$3/100,"yes","no")) | I11: =IF($E11="","",IF(LOWER(Settings!$B$4)="both",IF(AND($G11="yes",$H11="yes"),"yes","no"),IF(OR($G11="yes",$H11="yes"),"yes","no")))
A12: 6500 | B12: Professional fees | C12: 55000 | D12: 47500 | E12: =IF(OR($C12="",$D12=""),"",$D12-$C12) | F12: =IF(OR($C12="",$D12="",$C12=0),"",($D12-$C12)/ABS($C12)) | G12: =IF($E12="","",IF(ABS($E12)>Settings!$B$2,"yes","no")) | H12: =IF($F12="","",IF(ABS($F12)>=Settings!$B$3/100,"yes","no")) | I12: =IF($E12="","",IF(LOWER(Settings!$B$4)="both",IF(AND($G12="yes",$H12="yes"),"yes","no"),IF(OR($G12="yes",$H12="yes"),"yes","no")))
A13: 7000 | B13: Depreciation | C13: 128000 | D13: 128000 | E13: =IF(OR($C13="",$D13=""),"",$D13-$C13) | F13: =IF(OR($C13="",$D13="",$C13=0),"",($D13-$C13)/ABS($C13)) | G13: =IF($E13="","",IF(ABS($E13)>Settings!$B$2,"yes","no")) | H13: =IF($F13="","",IF(ABS($F13)>=Settings!$B$3/100,"yes","no")) | I13: =IF($E13="","",IF(LOWER(Settings!$B$4)="both",IF(AND($G13="yes",$H13="yes"),"yes","no"),IF(OR($G13="yes",$H13="yes"),"yes","no")))
... A15: 7400 | B15: Inventory shrink adjustment | C15: 6400 | D15: 8900 | E15: =IF(OR($C15="",$D15=""),"",$D15-$C15) | F15: =IF(OR($C15="",$D15="",$C15=0),"",($D15-$C15)/ABS($C15)) | G15: =IF($E15="","",IF(ABS($E15)>Settings!$B$2,"yes","no")) | H15: =IF($F15="","",IF(ABS($F15)>=Settings!$B$3/100,"yes","no")) | I15: =IF($E15="","",IF(LOWER(Settings!$B$4)="both",IF(AND($G15="yes",$H15="yes"),"yes","no"),IF(OR($G15="yes",$H15="yes"),"yes","no")))
E16: =IF(OR($C16="",$D16=""),"",$D16-$C16) | F16: =IF(OR($C16="",$D16="",$C16=0),"",($D16-$C16)/ABS($C16)) | G16: =IF($E16="","",IF(ABS($E16)>Settings!$B$2,"yes","no")) | H16: =IF($F16="","",IF(ABS($F16)>=Settings!$B$3/100,"yes","no")) | I16: =IF($E16="","",IF(LOWER(Settings!$B$4)="both",IF(AND($G16="yes",$H16="yes"),"yes","no"),IF(OR($G16="yes",$H16="yes"),"yes","no")))
E17: =IF(OR($C17="",$D17=""),"",$D17-$C17) | F17: =IF(OR($C17="",$D17="",$C17=0),"",($D17-$C17)/ABS($C17)) | G17: =IF($E17="","",IF(ABS($E17)>Settings!$B$2,"yes","no")) | H17: =IF($F17="","",IF(ABS($F17)>=Settings!$B$3/100,"yes","no")) | I17: =IF($E17="","",IF(LOWER(Settings!$B$4)="both",IF(AND($G17="yes",$H17="yes"),"yes","no"),IF(OR($G17="yes",$H17="yes"),"yes","no")))
E18: =IF(OR($C18="",$D18=""),"",$D18-$C18) | F18: =IF(OR($C18="",$D18="",$C18=0),"",($D18-$C18)/ABS($C18)) | G18: =IF($E18="","",IF(ABS($E18)>Settings!$B$2,"yes","no")) | H18: =IF($F18="","",IF(ABS($F18)>=Settings!$B$3/100,"yes","no")) | I18: =IF($E18="","",IF(LOWER(Settings!$B$4)="both",IF(AND($G18="yes",$H18="yes"),"yes","no"),IF(OR($G18="yes",$H18="yes"),"yes","no")))
E19: =IF(OR($C19="",$D19=""),"",$D19-$C19) | F19: =IF(OR($C19="",$D19="",$C19=0),"",($D19-$C19)/ABS($C19)) | G19: =IF($E19="","",IF(ABS($E19)>Settings!$B$2,"yes","no")) | H19: =IF($F19="","",IF(ABS($F19)>=Settings!$B$3/100,"yes","no")) | I19: =IF($E19="","",IF(LOWER(Settings!$B$4)="both",IF(AND($G19="yes",$H19="yes"),"yes","no"),IF(OR($G19="yes",$H19="yes"),"yes","no")))
E20: =IF(OR($C20="",$D20=""),"",$D20-$C20) | F20: =IF(OR($C20="",$D20="",$C20=0),"",($D20-$C20)/ABS($C20)) | G20: =IF($E20="","",IF(ABS($E20)>Settings!$B$2,"yes","no")) | H20: =IF($F20="","",IF(ABS($F20)>=Settings!$B$3/100,"yes","no")) | I20: =IF($E20="","",IF(LOWER(Settings!$B$4)="both",IF(AND($G20="yes",$H20="yes"),"yes","no"),IF(OR($G20="yes",$H20="yes"),"yes","no")))
E21: =IF(OR($C21="",$D21=""),"",$D21-$C21) | F21: =IF(OR($C21="",$D21="",$C21=0),"",($D21-$C21)/ABS($C21)) | G21: =IF($E21="","",IF(ABS($E21)>Settings!$B$2,"yes","no")) | H21: =IF($F21="","",IF(ABS($F21)>=Settings!$B$3/100,"yes","no")) | I21: =IF($E21="","",IF(LOWER(Settings!$B$4)="both",IF(AND($G21="yes",$H21="yes"),"yes","no"),IF(OR($G21="yes",$H21="yes"),"yes","no")))
E22: =IF(OR($C22="",$D22=""),"",$D22-$C22) | F22: =IF(OR($C22="",$D22="",$C22=0),"",($D22-$C22)/ABS($C22)) | G22: =IF($E22="","",IF(ABS($E22)>Settings!$B$2,"yes","no")) | H22: =IF($F22="","",IF(ABS($F22)>=Settings!$B$3/100,"yes","no")) | I22: =IF($E22="","",IF(LOWER(Settings!$B$4)="both",IF(AND($G22="yes",$H22="yes"),"yes","no"),IF(OR($G22="yes",$H22="yes"),"yes","no")))
E23: =IF(OR($C23="",$D23=""),"",$D23-$C23) | F23: =IF(OR($C23="",$D23="",$C23=0),"",($D23-$C23)/ABS($C23)) | G23: =IF($E23="","",IF(ABS($E23)>Settings!$B$2,"yes","no")) | H23: =IF($F23="","",IF(ABS($F23)>=Settings!$B$3/100,"yes","no")) | I23: =IF($E23="","",IF(LOWER(Settings!$B$4)="both",IF(AND($G23="yes",$H23="yes"),"yes","no"),IF(OR($G23="yes",$H23="yes"),"yes","no")))
E24: =IF(OR($C24="",$D24=""),"",$D24-$C24) | F24: =IF(OR($C24="",$D24="",$C24=0),"",($D24-$C24)/ABS($C24)) | G24: =IF($E24="","",IF(ABS($E24)>Settings!$B$2,"yes","no")) | H24: =IF($F24="","",IF(ABS($F24)>=Settings!$B$3/100,"yes","no")) | I24: =IF($E24="","",IF(LOWER(Settings!$B$4)="both",IF(AND($G24="yes",$H24="yes"),"yes","no"),IF(OR($G24="yes",$H24="yes"),"yes","no")))
E25: =IF(OR($C25="",$D25=""),"",$D25-$C25) | F25: =IF(OR($C25="",$D25="",$C25=0),"",($D25-$C25)/ABS($C25)) | G25: =IF($E25="","",IF(ABS($E25)>Settings!$B$2,"yes","no")) | H25: =IF($F25="","",IF(ABS($F25)>=Settings!$B$3/100,"yes","no")) | I25: =IF($E25="","",IF(LOWER(Settings!$B$4)="both",IF(AND($G25="yes",$H25="yes"),"yes","no"),IF(OR($G25="yes",$H25="yes"),"yes","no")))
E26: =IF(OR($C26="",$D26=""),"",$D26-$C26) | F26: =IF(OR($C26="",$D26="",$C26=0),"",($D26-$C26)/ABS($C26)) | G26: =IF($E26="","",IF(ABS($E26)>Settings!$B$2,"yes","no")) | H26: =IF($F26="","",IF(ABS($F26)>=Settings!$B$3/100,"yes","no")) | I26: =IF($E26="","",IF(LOWER(Settings!$B$4)="both",IF(AND($G26="yes",$H26="yes"),"yes","no"),IF(OR($G26="yes",$H26="yes"),"yes","no")))
E27: =IF(OR($C27="",$D27=""),"",$D27-$C27) | F27: =IF(OR($C27="",$D27="",$C27=0),"",($D27-$C27)/ABS($C27)) | G27: =IF($E27="","",IF(ABS($E27)>Settings!$B$2,"yes","no")) | H27: =IF($F27="","",IF(ABS($F27)>=Settings!$B$3/100,"yes","no")) | I27: =IF($E27="","",IF(LOWER(Settings!$B$4)="both",IF(AND($G27="yes",$H27="yes"),"yes","no"),IF(OR($G27="yes",$H27="yes"),"yes","no")))
... E45: =IF(OR($C45="",$D45=""),"",$D45-$C45) | F45: =IF(OR($C45="",$D45="",$C45=0),"",($D45-$C45)/ABS($C45)) | G45: =IF($E45="","",IF(ABS($E45)>Settings!$B$2,"yes","no")) | H45: =IF($F45="","",IF(ABS($F45)>=Settings!$B$3/100,"yes","no")) | I45: =IF($E45="","",IF(LOWER(Settings!$B$4)="both",IF(AND($G45="yes",$H45="yes"),"yes","no"),IF(OR($G45="yes",$H45="yes"),"yes","no")))

Sheet Settings
A1: Setting | B1: Value | C1: Note
A2: Dollar floor | B2: 25000 | C2: A movement must exceed this to clear the dollar leg.
A3: Percent floor (points) | B3: 10 | C3: A movement must reach this percent of the prior balance to clear the percent leg.
A4: Rule | B4: both | C4: both means a line owes commentary only when it clears both legs. either means one leg is enough.
A5: Close period | B5: June 2026, Halyard training case | C5: Rides along on the reviewer log so a filed log says which close it came from.
A6: Memo version | B6: Draft 2 | C6: The version of the commentary these results cover.
A7: Tie tolerance, dollars | B7: 1 | C7: A memo figure ties to the ledger when the two are within this many dollars.
A8: Tie tolerance, percentage points | B8: 0.05 | C8: A memo percent ties when the two are within this many points.

Sheet Memo
A1: Line | B1: Sentence | C1: Account | D1: Figure in sentence | E1: Figure basis | F1: Ledger figure | G1: Ties | H1: Direction stated | I1: Direction on ledger | J1: Direction ties | K1: Owes commentary | L1: Result
A2: S1 | B2: Depot repairs and maintenance of $118,600 reflects the roof and dock leveler program, which finished on June 30. | C2: 6200 | D2: 118600 | E2: Current | F2: =IF(OR($C2="",$E2=""),"",IFERROR(IF($E2="Percent",INDEX(Ledger!$F$2:$F$45,MATCH($C2,Ledger!$A$2:$A$45,0))*100,INDEX(Ledger!$C$2:$E$45,MATCH($C2,Ledger!$A$2:$A$45,0),MATCH($E2,{"Prior","Current","Change"},0))),"")) | G2: =IF(OR($D2="",$F2=""),"",IF(ABS(ABS($D2)-ABS($F2))<=IF($E2="Percent",Settings!$B$8,Settings!$B$7),"yes","no")) | H2: none | I2: =IF($C2="","",IFERROR(IF(INDEX(Ledger!$E$2:$E$45,MATCH($C2,Ledger!$A$2:$A$45,0))="","",IF(INDEX(Ledger!$E$2:$E$45,MATCH($C2,Ledger!$A$2:$A$45,0))>0,"up",IF(INDEX(Ledger!$E$2:$E$45,MATCH($C2,Ledger!$A$2:$A$45,0))<0,"down","none"))),"")) | J2: =IF(OR($H2="",$H2="none",$I2=""),"",IF($H2=$I2,"yes","no")) | K2: =IF($C2="","",IFERROR(INDEX(Ledger!$I$2:$I$45,MATCH($C2,Ledger!$A$2:$A$45,0)),"")) | L2: =IF($C2="","",IF(OR($G2="no",$J2="no"),"FAIL",IF($K2="no","INFO","REVIEW")))
A3: S2 | B3: Bad debt expense increased $42,000 following the reserve taken against the Coastal Grocers receivable. | C3: 6400 | D3: 42000 | E3: Change | F3: =IF(OR($C3="",$E3=""),"",IFERROR(IF($E3="Percent",INDEX(Ledger!$F$2:$F$45,MATCH($C3,Ledger!$A$2:$A$45,0))*100,INDEX(Ledger!$C$2:$E$45,MATCH($C3,Ledger!$A$2:$A$45,0),MATCH($E3,{"Prior","Current","Change"},0))),"")) | G3: =IF(OR($D3="",$F3=""),"",IF(ABS(ABS($D3)-ABS($F3))<=IF($E3="Percent",Settings!$B$8,Settings!$B$7),"yes","no")) | H3: up | I3: =IF($C3="","",IFERROR(IF(INDEX(Ledger!$E$2:$E$45,MATCH($C3,Ledger!$A$2:$A$45,0))="","",IF(INDEX(Ledger!$E$2:$E$45,MATCH($C3,Ledger!$A$2:$A$45,0))>0,"up",IF(INDEX(Ledger!$E$2:$E$45,MATCH($C3,Ledger!$A$2:$A$45,0))<0,"down","none"))),"")) | J3: =IF(OR($H3="",$H3="none",$I3=""),"",IF($H3=$I3,"yes","no")) | K3: =IF($C3="","",IFERROR(INDEX(Ledger!$I$2:$I$45,MATCH($C3,Ledger!$A$2:$A$45,0)),"")) | L3: =IF($C3="","",IF(OR($G3="no",$J3="no"),"FAIL",IF($K3="no","INFO","REVIEW")))
A4: S3 | B4: Software subscriptions rose $1,600, which clears neither leg of the threshold, so this line carries no driver. | C4: 6300 | D4: 1600 | E4: Change | F4: =IF(OR($C4="",$E4=""),"",IFERROR(IF($E4="Percent",INDEX(Ledger!$F$2:$F$45,MATCH($C4,Ledger!$A$2:$A$45,0))*100,INDEX(Ledger!$C$2:$E$45,MATCH($C4,Ledger!$A$2:$A$45,0),MATCH($E4,{"Prior","Current","Change"},0))),"")) | G4: =IF(OR($D4="",$F4=""),"",IF(ABS(ABS($D4)-ABS($F4))<=IF($E4="Percent",Settings!$B$8,Settings!$B$7),"yes","no")) | H4: up | I4: =IF($C4="","",IFERROR(IF(INDEX(Ledger!$E$2:$E$45,MATCH($C4,Ledger!$A$2:$A$45,0))="","",IF(INDEX(Ledger!$E$2:$E$45,MATCH($C4,Ledger!$A$2:$A$45,0))>0,"up",IF(INDEX(Ledger!$E$2:$E$45,MATCH($C4,Ledger!$A$2:$A$45,0))<0,"down","none"))),"")) | J4: =IF(OR($H4="",$H4="none",$I4=""),"",IF($H4=$I4,"yes","no")) | K4: =IF($C4="","",IFERROR(INDEX(Ledger!$I$2:$I$45,MATCH($C4,Ledger!$A$2:$A$45,0)),"")) | L4: =IF($C4="","",IF(OR($G4="no",$J4="no"),"FAIL",IF($K4="no","INFO","REVIEW")))
A5: S4 | B5: Distribution revenue of $5,612,000 grew 7.1 percent over May on continued customer demand across all four depots. | C5: 4000 | D5: 5612000 | E5: Current | F5: =IF(OR($C5="",$E5=""),"",IFERROR(IF($E5="Percent",INDEX(Ledger!$F$2:$F$45,MATCH($C5,Ledger!$A$2:$A$45,0))*100,INDEX(Ledger!$C$2:$E$45,MATCH($C5,Ledger!$A$2:$A$45,0),MATCH($E5,{"Prior","Current","Change"},0))),"")) | G5: =IF(OR($D5="",$F5=""),"",IF(ABS(ABS($D5)-ABS($F5))<=IF($E5="Percent",Settings!$B$8,Settings!$B$7),"yes","no")) | H5: up | I5: =IF($C5="","",IFERROR(IF(INDEX(Ledger!$E$2:$E$45,MATCH($C5,Ledger!$A$2:$A$45,0))="","",IF(INDEX(Ledger!$E$2:$E$45,MATCH($C5,Ledger!$A$2:$A$45,0))>0,"up",IF(INDEX(Ledger!$E$2:$E$45,MATCH($C5,Ledger!$A$2:$A$45,0))<0,"down","none"))),"")) | J5: =IF(OR($H5="",$H5="none",$I5=""),"",IF($H5=$I5,"yes","no")) | K5: =IF($C5="","",IFERROR(INDEX(Ledger!$I$2:$I$45,MATCH($C5,Ledger!$A$2:$A$45,0)),"")) | L5: =IF($C5="","",IF(OR($G5="no",$J5="no"),"FAIL",IF($K5="no","INFO","REVIEW")))
A6: S5 | B6: The growth in both revenue lines is driven by the Tri-State depot ramp, which management expects to continue through the third quarter. | C6: 4100 | F6: =IF(OR($C6="",$E6=""),"",IFERROR(IF($E6="Percent",INDEX(Ledger!$F$2:$F$45,MATCH($C6,Ledger!$A$2:$A$45,0))*100,INDEX(Ledger!$C$2:$E$45,MATCH($C6,Ledger!$A$2:$A$45,0),MATCH($E6,{"Prior","Current","Change"},0))),"")) | G6: =IF(OR($D6="",$F6=""),"",IF(ABS(ABS($D6)-ABS($F6))<=IF($E6="Percent",Settings!$B$8,Settings!$B$7),"yes","no")) | H6: up | I6: =IF($C6="","",IFERROR(IF(INDEX(Ledger!$E$2:$E$45,MATCH($C6,Ledger!$A$2:$A$45,0))="","",IF(INDEX(Ledger!$E$2:$E$45,MATCH($C6,Ledger!$A$2:$A$45,0))>0,"up",IF(INDEX(Ledger!$E$2:$E$45,MATCH($C6,Ledger!$A$2:$A$45,0))<0,"down","none"))),"")) | J6: =IF(OR($H6="",$H6="none",$I6=""),"",IF($H6=$I6,"yes","no")) | K6: =IF($C6="","",IFERROR(INDEX(Ledger!$I$2:$I$45,MATCH($C6,Ledger!$A$2:$A$45,0)),"")) | L6: =IF($C6="","",IF(OR($G6="no",$J6="no"),"FAIL",IF($K6="no","INFO","REVIEW")))
A7: S6 | B7: Inbound freight declined to $287,800 as carrier fuel surcharges eased. | C7: 5100 | D7: 287800 | E7: Current | F7: =IF(OR($C7="",$E7=""),"",IFERROR(IF($E7="Percent",INDEX(Ledger!$F$2:$F$45,MATCH($C7,Ledger!$A$2:$A$45,0))*100,INDEX(Ledger!$C$2:$E$45,MATCH($C7,Ledger!$A$2:$A$45,0),MATCH($E7,{"Prior","Current","Change"},0))),"")) | G7: =IF(OR($D7="",$F7=""),"",IF(ABS(ABS($D7)-ABS($F7))<=IF($E7="Percent",Settings!$B$8,Settings!$B$7),"yes","no")) | H7: down | I7: =IF($C7="","",IFERROR(IF(INDEX(Ledger!$E$2:$E$45,MATCH($C7,Ledger!$A$2:$A$45,0))="","",IF(INDEX(Ledger!$E$2:$E$45,MATCH($C7,Ledger!$A$2:$A$45,0))>0,"up",IF(INDEX(Ledger!$E$2:$E$45,MATCH($C7,Ledger!$A$2:$A$45,0))<0,"down","none"))),"")) | J7: =IF(OR($H7="",$H7="none",$I7=""),"",IF($H7=$I7,"yes","no")) | K7: =IF($C7="","",IFERROR(INDEX(Ledger!$I$2:$I$45,MATCH($C7,Ledger!$A$2:$A$45,0)),"")) | L7: =IF($C7="","",IF(OR($G7="no",$J7="no"),"FAIL",IF($K7="no","INFO","REVIEW")))
A8: S7 | B8: Interest expense rose $31,200 on the depot equipment additions that also sit in depreciation. | C8: 7100 | D8: 31200 | E8: Change | F8: =IF(OR($C8="",$E8=""),"",IFERROR(IF($E8="Percent",INDEX(Ledger!$F$2:$F$45,MATCH($C8,Ledger!$A$2:$A$45,0))*100,INDEX(Ledger!$C$2:$E$45,MATCH($C8,Ledger!$A$2:$A$45,0),MATCH($E8,{"Prior","Current","Change"},0))),"")) | G8: =IF(OR($D8="",$F8=""),"",IF(ABS(ABS($D8)-ABS($F8))<=IF($E8="Percent",Settings!$B$8,Settings!$B$7),"yes","no")) | H8: up | I8: =IF($C8="","",IFERROR(IF(INDEX(Ledger!$E$2:$E$45,MATCH($C8,Ledger!$A$2:$A$45,0))="","",IF(INDEX(Ledger!$E$2:$E$45,MATCH($C8,Ledger!$A$2:$A$45,0))>0,"up",IF(INDEX(Ledger!$E$2:$E$45,MATCH($C8,Ledger!$A$2:$A$45,0))<0,"down","none"))),"")) | J8: =IF(OR($H8="",$H8="none",$I8=""),"",IF($H8=$I8,"yes","no")) | K8: =IF($C8="","",IFERROR(INDEX(Ledger!$I$2:$I$45,MATCH($C8,Ledger!$A$2:$A$45,0)),"")) | L8: =IF($C8="","",IF(OR($G8="no",$J8="no"),"FAIL",IF($K8="no","INFO","REVIEW")))
A9: S8 | B9: Fleet fuel fell $5,200 on lower pump prices through June, and the movement fails both legs of the threshold, so the line owes no commentary at all. Every June fuel invoice from the fleet servicer was received and recorded before the books closed. | C9: 6100 | D9: 5200 | E9: Change | F9: =IF(OR($C9="",$E9=""),"",IFERROR(IF($E9="Percent",INDEX(Ledger!$F$2:$F$45,MATCH($C9,Ledger!$A$2:$A$45,0))*100,INDEX(Ledger!$C$2:$E$45,MATCH($C9,Ledger!$A$2:$A$45,0),MATCH($E9,{"Prior","Current","Change"},0))),"")) | G9: =IF(OR($D9="",$F9=""),"",IF(ABS(ABS($D9)-ABS($F9))<=IF($E9="Percent",Settings!$B$8,Settings!$B$7),"yes","no")) | H9: down | I9: =IF($C9="","",IFERROR(IF(INDEX(Ledger!$E$2:$E$45,MATCH($C9,Ledger!$A$2:$A$45,0))="","",IF(INDEX(Ledger!$E$2:$E$45,MATCH($C9,Ledger!$A$2:$A$45,0))>0,"up",IF(INDEX(Ledger!$E$2:$E$45,MATCH($C9,Ledger!$A$2:$A$45,0))<0,"down","none"))),"")) | J9: =IF(OR($H9="",$H9="none",$I9=""),"",IF($H9=$I9,"yes","no")) | K9: =IF($C9="","",IFERROR(INDEX(Ledger!$I$2:$I$45,MATCH($C9,Ledger!$A$2:$A$45,0)),"")) | L9: =IF($C9="","",IF(OR($G9="no",$J9="no"),"FAIL",IF($K9="no","INFO","REVIEW")))
A10: S9 | B10: Service revenue rose $229,000 as the equipment maintenance contracts signed in the spring moved onto monthly billing in June, and each month's fee is earned in the month it covers. | C10: 4100 | D10: 229000 | E10: Change | F10: =IF(OR($C10="",$E10=""),"",IFERROR(IF($E10="Percent",INDEX(Ledger!$F$2:$F$45,MATCH($C10,Ledger!$A$2:$A$45,0))*100,INDEX(Ledger!$C$2:$E$45,MATCH($C10,Ledger!$A$2:$A$45,0),MATCH($E10,{"Prior","Current","Change"},0))),"")) | G10: =IF(OR($D10="",$F10=""),"",IF(ABS(ABS($D10)-ABS($F10))<=IF($E10="Percent",Settings!$B$8,Settings!$B$7),"yes","no")) | H10: up | I10: =IF($C10="","",IFERROR(IF(INDEX(Ledger!$E$2:$E$45,MATCH($C10,Ledger!$A$2:$A$45,0))="","",IF(INDEX(Ledger!$E$2:$E$45,MATCH($C10,Ledger!$A$2:$A$45,0))>0,"up",IF(INDEX(Ledger!$E$2:$E$45,MATCH($C10,Ledger!$A$2:$A$45,0))<0,"down","none"))),"")) | J10: =IF(OR($H10="",$H10="none",$I10=""),"",IF($H10=$I10,"yes","no")) | K10: =IF($C10="","",IFERROR(INDEX(Ledger!$I$2:$I$45,MATCH($C10,Ledger!$A$2:$A$45,0)),"")) | L10: =IF($C10="","",IF(OR($G10="no",$J10="no"),"FAIL",IF($K10="no","INFO","REVIEW")))
A11: S10 | B11: The remaining depot repairs are scheduled to finish in August, and that spend is not yet in these numbers. | C11: 6200 | F11: =IF(OR($C11="",$E11=""),"",IFERROR(IF($E11="Percent",INDEX(Ledger!$F$2:$F$45,MATCH($C11,Ledger!$A$2:$A$45,0))*100,INDEX(Ledger!$C$2:$E$45,MATCH($C11,Ledger!$A$2:$A$45,0),MATCH($E11,{"Prior","Current","Change"},0))),"")) | G11: =IF(OR($D11="",$F11=""),"",IF(ABS(ABS($D11)-ABS($F11))<=IF($E11="Percent",Settings!$B$8,Settings!$B$7),"yes","no")) | H11: none | I11: =IF($C11="","",IFERROR(IF(INDEX(Ledger!$E$2:$E$45,MATCH($C11,Ledger!$A$2:$A$45,0))="","",IF(INDEX(Ledger!$E$2:$E$45,MATCH($C11,Ledger!$A$2:$A$45,0))>0,"up",IF(INDEX(Ledger!$E$2:$E$45,MATCH($C11,Ledger!$A$2:$A$45,0))<0,"down","none"))),"")) | J11: =IF(OR($H11="",$H11="none",$I11=""),"",IF($H11=$I11,"yes","no")) | K11: =IF($C11="","",IFERROR(INDEX(Ledger!$I$2:$I$45,MATCH($C11,Ledger!$A$2:$A$45,0)),"")) | L11: =IF($C11="","",IF(OR($G11="no",$J11="no"),"FAIL",IF($K11="no","INFO","REVIEW")))
A12: S11 | B12: Cost of product sold rose $348,000 against a $372,000 rise in revenue, so product gross margin fell from 25.0 percent in May to 23.8 percent in June on a shift toward lower margin lines. | C12: 5000 | D12: 348000 | E12: Change | F12: =IF(OR($C12="",$E12=""),"",IFERROR(IF($E12="Percent",INDEX(Ledger!$F$2:$F$45,MATCH($C12,Ledger!$A$2:$A$45,0))*100,INDEX(Ledger!$C$2:$E$45,MATCH($C12,Ledger!$A$2:$A$45,0),MATCH($E12,{"Prior","Current","Change"},0))),"")) | G12: =IF(OR($D12="",$F12=""),"",IF(ABS(ABS($D12)-ABS($F12))<=IF($E12="Percent",Settings!$B$8,Settings!$B$7),"yes","no")) | H12: up | I12: =IF($C12="","",IFERROR(IF(INDEX(Ledger!$E$2:$E$45,MATCH($C12,Ledger!$A$2:$A$45,0))="","",IF(INDEX(Ledger!$E$2:$E$45,MATCH($C12,Ledger!$A$2:$A$45,0))>0,"up",IF(INDEX(Ledger!$E$2:$E$45,MATCH($C12,Ledger!$A$2:$A$45,0))<0,"down","none"))),"")) | J12: =IF(OR($H12="",$H12="none",$I12=""),"",IF($H12=$I12,"yes","no")) | K12: =IF($C12="","",IFERROR(INDEX(Ledger!$I$2:$I$45,MATCH($C12,Ledger!$A$2:$A$45,0)),"")) | L12: =IF($C12="","",IF(OR($G12="no",$J12="no"),"FAIL",IF($K12="no","INFO","REVIEW")))
A13: S12 | B13: Professional fees fell $7,500 because May carried a one-time $7,500 invoice from outside counsel for the depot lease renewal review, and the movement fails the dollar leg of the threshold. | C13: 6500 | D13: 7500 | E13: Change | F13: =IF(OR($C13="",$E13=""),"",IFERROR(IF($E13="Percent",INDEX(Ledger!$F$2:$F$45,MATCH($C13,Ledger!$A$2:$A$45,0))*100,INDEX(Ledger!$C$2:$E$45,MATCH($C13,Ledger!$A$2:$A$45,0),MATCH($E13,{"Prior","Current","Change"},0))),"")) | G13: =IF(OR($D13="",$F13=""),"",IF(ABS(ABS($D13)-ABS($F13))<=IF($E13="Percent",Settings!$B$8,Settings!$B$7),"yes","no")) | H13: down | I13: =IF($C13="","",IFERROR(IF(INDEX(Ledger!$E$2:$E$45,MATCH($C13,Ledger!$A$2:$A$45,0))="","",IF(INDEX(Ledger!$E$2:$E$45,MATCH($C13,Ledger!$A$2:$A$45,0))>0,"up",IF(INDEX(Ledger!$E$2:$E$45,MATCH($C13,Ledger!$A$2:$A$45,0))<0,"down","none"))),"")) | J13: =IF(OR($H13="",$H13="none",$I13=""),"",IF($H13=$I13,"yes","no")) | K13: =IF($C13="","",IFERROR(INDEX(Ledger!$I$2:$I$45,MATCH($C13,Ledger!$A$2:$A$45,0)),"")) | L13: =IF($C13="","",IF(OR($G13="no",$J13="no"),"FAIL",IF($K13="no","INFO","REVIEW")))
F14: =IF(OR($C14="",$E14=""),"",IFERROR(IF($E14="Percent",INDEX(Ledger!$F$2:$F$45,MATCH($C14,Ledger!$A$2:$A$45,0))*100,INDEX(Ledger!$C$2:$E$45,MATCH($C14,Ledger!$A$2:$A$45,0),MATCH($E14,{"Prior","Current","Change"},0))),"")) | G14: =IF(OR($D14="",$F14=""),"",IF(ABS(ABS($D14)-ABS($F14))<=IF($E14="Percent",Settings!$B$8,Settings!$B$7),"yes","no")) | I14: =IF($C14="","",IFERROR(IF(INDEX(Ledger!$E$2:$E$45,MATCH($C14,Ledger!$A$2:$A$45,0))="","",IF(INDEX(Ledger!$E$2:$E$45,MATCH($C14,Ledger!$A$2:$A$45,0))>0,"up",IF(INDEX(Ledger!$E$2:$E$45,MATCH($C14,Ledger!$A$2:$A$45,0))<0,"down","none"))),"")) | J14: =IF(OR($H14="",$H14="none",$I14=""),"",IF($H14=$I14,"yes","no")) | K14: =IF($C14="","",IFERROR(INDEX(Ledger!$I$2:$I$45,MATCH($C14,Ledger!$A$2:$A$45,0)),"")) | L14: =IF($C14="","",IF(OR($G14="no",$J14="no"),"FAIL",IF($K14="no","INFO","REVIEW")))
F15: =IF(OR($C15="",$E15=""),"",IFERROR(IF($E15="Percent",INDEX(Ledger!$F$2:$F$45,MATCH($C15,Ledger!$A$2:$A$45,0))*100,INDEX(Ledger!$C$2:$E$45,MATCH($C15,Ledger!$A$2:$A$45,0),MATCH($E15,{"Prior","Current","Change"},0))),"")) | G15: =IF(OR($D15="",$F15=""),"",IF(ABS(ABS($D15)-ABS($F15))<=IF($E15="Percent",Settings!$B$8,Settings!$B$7),"yes","no")) | I15: =IF($C15="","",IFERROR(IF(INDEX(Ledger!$E$2:$E$45,MATCH($C15,Ledger!$A$2:$A$45,0))="","",IF(INDEX(Ledger!$E$2:$E$45,MATCH($C15,Ledger!$A$2:$A$45,0))>0,"up",IF(INDEX(Ledger!$E$2:$E$45,MATCH($C15,Ledger!$A$2:$A$45,0))<0,"down","none"))),"")) | J15: =IF(OR($H15="",$H15="none",$I15=""),"",IF($H15=$I15,"yes","no")) | K15: =IF($C15="","",IFERROR(INDEX(Ledger!$I$2:$I$45,MATCH($C15,Ledger!$A$2:$A$45,0)),"")) | L15: =IF($C15="","",IF(OR($G15="no",$J15="no"),"FAIL",IF($K15="no","INFO","REVIEW")))
F16: =IF(OR($C16="",$E16=""),"",IFERROR(IF($E16="Percent",INDEX(Ledger!$F$2:$F$45,MATCH($C16,Ledger!$A$2:$A$45,0))*100,INDEX(Ledger!$C$2:$E$45,MATCH($C16,Ledger!$A$2:$A$45,0),MATCH($E16,{"Prior","Current","Change"},0))),"")) | G16: =IF(OR($D16="",$F16=""),"",IF(ABS(ABS($D16)-ABS($F16))<=IF($E16="Percent",Settings!$B$8,Settings!$B$7),"yes","no")) | I16: =IF($C16="","",IFERROR(IF(INDEX(Ledger!$E$2:$E$45,MATCH($C16,Ledger!$A$2:$A$45,0))="","",IF(INDEX(Ledger!$E$2:$E$45,MATCH($C16,Ledger!$A$2:$A$45,0))>0,"up",IF(INDEX(Ledger!$E$2:$E$45,MATCH($C16,Ledger!$A$2:$A$45,0))<0,"down","none"))),"")) | J16: =IF(OR($H16="",$H16="none",$I16=""),"",IF($H16=$I16,"yes","no")) | K16: =IF($C16="","",IFERROR(INDEX(Ledger!$I$2:$I$45,MATCH($C16,Ledger!$A$2:$A$45,0)),"")) | L16: =IF($C16="","",IF(OR($G16="no",$J16="no"),"FAIL",IF($K16="no","INFO","REVIEW")))
F17: =IF(OR($C17="",$E17=""),"",IFERROR(IF($E17="Percent",INDEX(Ledger!$F$2:$F$45,MATCH($C17,Ledger!$A$2:$A$45,0))*100,INDEX(Ledger!$C$2:$E$45,MATCH($C17,Ledger!$A$2:$A$45,0),MATCH($E17,{"Prior","Current","Change"},0))),"")) | G17: =IF(OR($D17="",$F17=""),"",IF(ABS(ABS($D17)-ABS($F17))<=IF($E17="Percent",Settings!$B$8,Settings!$B$7),"yes","no")) | I17: =IF($C17="","",IFERROR(IF(INDEX(Ledger!$E$2:$E$45,MATCH($C17,Ledger!$A$2:$A$45,0))="","",IF(INDEX(Ledger!$E$2:$E$45,MATCH($C17,Ledger!$A$2:$A$45,0))>0,"up",IF(INDEX(Ledger!$E$2:$E$45,MATCH($C17,Ledger!$A$2:$A$45,0))<0,"down","none"))),"")) | J17: =IF(OR($H17="",$H17="none",$I17=""),"",IF($H17=$I17,"yes","no")) | K17: =IF($C17="","",IFERROR(INDEX(Ledger!$I$2:$I$45,MATCH($C17,Ledger!$A$2:$A$45,0)),"")) | L17: =IF($C17="","",IF(OR($G17="no",$J17="no"),"FAIL",IF($K17="no","INFO","REVIEW")))
F18: =IF(OR($C18="",$E18=""),"",IFERROR(IF($E18="Percent",INDEX(Ledger!$F$2:$F$45,MATCH($C18,Ledger!$A$2:$A$45,0))*100,INDEX(Ledger!$C$2:$E$45,MATCH($C18,Ledger!$A$2:$A$45,0),MATCH($E18,{"Prior","Current","Change"},0))),"")) | G18: =IF(OR($D18="",$F18=""),"",IF(ABS(ABS($D18)-ABS($F18))<=IF($E18="Percent",Settings!$B$8,Settings!$B$7),"yes","no")) | I18: =IF($C18="","",IFERROR(IF(INDEX(Ledger!$E$2:$E$45,MATCH($C18,Ledger!$A$2:$A$45,0))="","",IF(INDEX(Ledger!$E$2:$E$45,MATCH($C18,Ledger!$A$2:$A$45,0))>0,"up",IF(INDEX(Ledger!$E$2:$E$45,MATCH($C18,Ledger!$A$2:$A$45,0))<0,"down","none"))),"")) | J18: =IF(OR($H18="",$H18="none",$I18=""),"",IF($H18=$I18,"yes","no")) | K18: =IF($C18="","",IFERROR(INDEX(Ledger!$I$2:$I$45,MATCH($C18,Ledger!$A$2:$A$45,0)),"")) | L18: =IF($C18="","",IF(OR($G18="no",$J18="no"),"FAIL",IF($K18="no","INFO","REVIEW")))
F19: =IF(OR($C19="",$E19=""),"",IFERROR(IF($E19="Percent",INDEX(Ledger!$F$2:$F$45,MATCH($C19,Ledger!$A$2:$A$45,0))*100,INDEX(Ledger!$C$2:$E$45,MATCH($C19,Ledger!$A$2:$A$45,0),MATCH($E19,{"Prior","Current","Change"},0))),"")) | G19: =IF(OR($D19="",$F19=""),"",IF(ABS(ABS($D19)-ABS($F19))<=IF($E19="Percent",Settings!$B$8,Settings!$B$7),"yes","no")) | I19: =IF($C19="","",IFERROR(IF(INDEX(Ledger!$E$2:$E$45,MATCH($C19,Ledger!$A$2:$A$45,0))="","",IF(INDEX(Ledger!$E$2:$E$45,MATCH($C19,Ledger!$A$2:$A$45,0))>0,"up",IF(INDEX(Ledger!$E$2:$E$45,MATCH($C19,Ledger!$A$2:$A$45,0))<0,"down","none"))),"")) | J19: =IF(OR($H19="",$H19="none",$I19=""),"",IF($H19=$I19,"yes","no")) | K19: =IF($C19="","",IFERROR(INDEX(Ledger!$I$2:$I$45,MATCH($C19,Ledger!$A$2:$A$45,0)),"")) | L19: =IF($C19="","",IF(OR($G19="no",$J19="no"),"FAIL",IF($K19="no","INFO","REVIEW")))
F20: =IF(OR($C20="",$E20=""),"",IFERROR(IF($E20="Percent",INDEX(Ledger!$F$2:$F$45,MATCH($C20,Ledger!$A$2:$A$45,0))*100,INDEX(Ledger!$C$2:$E$45,MATCH($C20,Ledger!$A$2:$A$45,0),MATCH($E20,{"Prior","Current","Change"},0))),"")) | G20: =IF(OR($D20="",$F20=""),"",IF(ABS(ABS($D20)-ABS($F20))<=IF($E20="Percent",Settings!$B$8,Settings!$B$7),"yes","no")) | I20: =IF($C20="","",IFERROR(IF(INDEX(Ledger!$E$2:$E$45,MATCH($C20,Ledger!$A$2:$A$45,0))="","",IF(INDEX(Ledger!$E$2:$E$45,MATCH($C20,Ledger!$A$2:$A$45,0))>0,"up",IF(INDEX(Ledger!$E$2:$E$45,MATCH($C20,Ledger!$A$2:$A$45,0))<0,"down","none"))),"")) | J20: =IF(OR($H20="",$H20="none",$I20=""),"",IF($H20=$I20,"yes","no")) | K20: =IF($C20="","",IFERROR(INDEX(Ledger!$I$2:$I$45,MATCH($C20,Ledger!$A$2:$A$45,0)),"")) | L20: =IF($C20="","",IF(OR($G20="no",$J20="no"),"FAIL",IF($K20="no","INFO","REVIEW")))
F21: =IF(OR($C21="",$E21=""),"",IFERROR(IF($E21="Percent",INDEX(Ledger!$F$2:$F$45,MATCH($C21,Ledger!$A$2:$A$45,0))*100,INDEX(Ledger!$C$2:$E$45,MATCH($C21,Ledger!$A$2:$A$45,0),MATCH($E21,{"Prior","Current","Change"},0))),"")) | G21: =IF(OR($D21="",$F21=""),"",IF(ABS(ABS($D21)-ABS($F21))<=IF($E21="Percent",Settings!$B$8,Settings!$B$7),"yes","no")) | I21: =IF($C21="","",IFERROR(IF(INDEX(Ledger!$E$2:$E$45,MATCH($C21,Ledger!$A$2:$A$45,0))="","",IF(INDEX(Ledger!$E$2:$E$45,MATCH($C21,Ledger!$A$2:$A$45,0))>0,"up",IF(INDEX(Ledger!$E$2:$E$45,MATCH($C21,Ledger!$A$2:$A$45,0))<0,"down","none"))),"")) | J21: =IF(OR($H21="",$H21="none",$I21=""),"",IF($H21=$I21,"yes","no")) | K21: =IF($C21="","",IFERROR(INDEX(Ledger!$I$2:$I$45,MATCH($C21,Ledger!$A$2:$A$45,0)),"")) | L21: =IF($C21="","",IF(OR($G21="no",$J21="no"),"FAIL",IF($K21="no","INFO","REVIEW")))
F22: =IF(OR($C22="",$E22=""),"",IFERROR(IF($E22="Percent",INDEX(Ledger!$F$2:$F$45,MATCH($C22,Ledger!$A$2:$A$45,0))*100,INDEX(Ledger!$C$2:$E$45,MATCH($C22,Ledger!$A$2:$A$45,0),MATCH($E22,{"Prior","Current","Change"},0))),"")) | G22: =IF(OR($D22="",$F22=""),"",IF(ABS(ABS($D22)-ABS($F22))<=IF($E22="Percent",Settings!$B$8,Settings!$B$7),"yes","no")) | I22: =IF($C22="","",IFERROR(IF(INDEX(Ledger!$E$2:$E$45,MATCH($C22,Ledger!$A$2:$A$45,0))="","",IF(INDEX(Ledger!$E$2:$E$45,MATCH($C22,Ledger!$A$2:$A$45,0))>0,"up",IF(INDEX(Ledger!$E$2:$E$45,MATCH($C22,Ledger!$A$2:$A$45,0))<0,"down","none"))),"")) | J22: =IF(OR($H22="",$H22="none",$I22=""),"",IF($H22=$I22,"yes","no")) | K22: =IF($C22="","",IFERROR(INDEX(Ledger!$I$2:$I$45,MATCH($C22,Ledger!$A$2:$A$45,0)),"")) | L22: =IF($C22="","",IF(OR($G22="no",$J22="no"),"FAIL",IF($K22="no","INFO","REVIEW")))
F23: =IF(OR($C23="",$E23=""),"",IFERROR(IF($E23="Percent",INDEX(Ledger!$F$2:$F$45,MATCH($C23,Ledger!$A$2:$A$45,0))*100,INDEX(Ledger!$C$2:$E$45,MATCH($C23,Ledger!$A$2:$A$45,0),MATCH($E23,{"Prior","Current","Change"},0))),"")) | G23: =IF(OR($D23="",$F23=""),"",IF(ABS(ABS($D23)-ABS($F23))<=IF($E23="Percent",Settings!$B$8,Settings!$B$7),"yes","no")) | I23: =IF($C23="","",IFERROR(IF(INDEX(Ledger!$E$2:$E$45,MATCH($C23,Ledger!$A$2:$A$45,0))="","",IF(INDEX(Ledger!$E$2:$E$45,MATCH($C23,Ledger!$A$2:$A$45,0))>0,"up",IF(INDEX(Ledger!$E$2:$E$45,MATCH($C23,Ledger!$A$2:$A$45,0))<0,"down","none"))),"")) | J23: =IF(OR($H23="",$H23="none",$I23=""),"",IF($H23=$I23,"yes","no")) | K23: =IF($C23="","",IFERROR(INDEX(Ledger!$I$2:$I$45,MATCH($C23,Ledger!$A$2:$A$45,0)),"")) | L23: =IF($C23="","",IF(OR($G23="no",$J23="no"),"FAIL",IF($K23="no","INFO","REVIEW")))
F24: =IF(OR($C24="",$E24=""),"",IFERROR(IF($E24="Percent",INDEX(Ledger!$F$2:$F$45,MATCH($C24,Ledger!$A$2:$A$45,0))*100,INDEX(Ledger!$C$2:$E$45,MATCH($C24,Ledger!$A$2:$A$45,0),MATCH($E24,{"Prior","Current","Change"},0))),"")) | G24: =IF(OR($D24="",$F24=""),"",IF(ABS(ABS($D24)-ABS($F24))<=IF($E24="Percent",Settings!$B$8,Settings!$B$7),"yes","no")) | I24: =IF($C24="","",IFERROR(IF(INDEX(Ledger!$E$2:$E$45,MATCH($C24,Ledger!$A$2:$A$45,0))="","",IF(INDEX(Ledger!$E$2:$E$45,MATCH($C24,Ledger!$A$2:$A$45,0))>0,"up",IF(INDEX(Ledger!$E$2:$E$45,MATCH($C24,Ledger!$A$2:$A$45,0))<0,"down","none"))),"")) | J24: =IF(OR($H24="",$H24="none",$I24=""),"",IF($H24=$I24,"yes","no")) | K24: =IF($C24="","",IFERROR(INDEX(Ledger!$I$2:$I$45,MATCH($C24,Ledger!$A$2:$A$45,0)),"")) | L24: =IF($C24="","",IF(OR($G24="no",$J24="no"),"FAIL",IF($K24="no","INFO","REVIEW")))
F25: =IF(OR($C25="",$E25=""),"",IFERROR(IF($E25="Percent",INDEX(Ledger!$F$2:$F$45,MATCH($C25,Ledger!$A$2:$A$45,0))*100,INDEX(Ledger!$C$2:$E$45,MATCH($C25,Ledger!$A$2:$A$45,0),MATCH($E25,{"Prior","Current","Change"},0))),"")) | G25: =IF(OR($D25="",$F25=""),"",IF(ABS(ABS($D25)-ABS($F25))<=IF($E25="Percent",Settings!$B$8,Settings!$B$7),"yes","no")) | I25: =IF($C25="","",IFERROR(IF(INDEX(Ledger!$E$2:$E$45,MATCH($C25,Ledger!$A$2:$A$45,0))="","",IF(INDEX(Ledger!$E$2:$E$45,MATCH($C25,Ledger!$A$2:$A$45,0))>0,"up",IF(INDEX(Ledger!$E$2:$E$45,MATCH($C25,Ledger!$A$2:$A$45,0))<0,"down","none"))),"")) | J25: =IF(OR($H25="",$H25="none",$I25=""),"",IF($H25=$I25,"yes","no")) | K25: =IF($C25="","",IFERROR(INDEX(Ledger!$I$2:$I$45,MATCH($C25,Ledger!$A$2:$A$45,0)),"")) | L25: =IF($C25="","",IF(OR($G25="no",$J25="no"),"FAIL",IF($K25="no","INFO","REVIEW")))
... F43: =IF(OR($C43="",$E43=""),"",IFERROR(IF($E43="Percent",INDEX(Ledger!$F$2:$F$45,MATCH($C43,Ledger!$A$2:$A$45,0))*100,INDEX(Ledger!$C$2:$E$45,MATCH($C43,Ledger!$A$2:$A$45,0),MATCH($E43,{"Prior","Current","Change"},0))),"")) | G43: =IF(OR($D43="",$F43=""),"",IF(ABS(ABS($D43)-ABS($F43))<=IF($E43="Percent",Settings!$B$8,Settings!$B$7),"yes","no")) | I43: =IF($C43="","",IFERROR(IF(INDEX(Ledger!$E$2:$E$45,MATCH($C43,Ledger!$A$2:$A$45,0))="","",IF(INDEX(Ledger!$E$2:$E$45,MATCH($C43,Ledger!$A$2:$A$45,0))>0,"up",IF(INDEX(Ledger!$E$2:$E$45,MATCH($C43,Ledger!$A$2:$A$45,0))<0,"down","none"))),"")) | J43: =IF(OR($H43="",$H43="none",$I43=""),"",IF($H43=$I43,"yes","no")) | K43: =IF($C43="","",IFERROR(INDEX(Ledger!$I$2:$I$45,MATCH($C43,Ledger!$A$2:$A$45,0)),"")) | L43: =IF($C43="","",IF(OR($G43="no",$J43="no"),"FAIL",IF($K43="no","INFO","REVIEW")))

Sheet Silence
A1: Owes an explanation, none written
A2: Every account that clears the rule on Settings and carries no sentence on the Memo sheet. These go to the controller as a question, not to the preparer as a correction.
A3: Silent lines: | B3: =COUNTIF($G$6:$G$49,"Owes an explanation, none written")
A5: Account | B5: Name | C5: Change | D5: Percent | E5: Owes commentary | F5: Sentences on this account | G5: Status
A6: =IF(Ledger!$A2="","",Ledger!$A2) | B6: =IF(Ledger!$A2="","",Ledger!$B2) | C6: =IF(Ledger!$A2="","",Ledger!$E2) | D6: =IF(Ledger!$A2="","",Ledger!$F2) | E6: =IF(Ledger!$A2="","",Ledger!$I2) | F6: =IF(Ledger!$A2="","",COUNTIF(Memo!$C$2:$C$43,Ledger!$A2)) | G6: =IF($A6="","",IF($E6<>"yes","No commentary owed",IF($F6=0,"Owes an explanation, none written","Explained, "&$F6&" sentence(s) on this account")))
A7: =IF(Ledger!$A3="","",Ledger!$A3) | B7: =IF(Ledger!$A3="","",Ledger!$B3) | C7: =IF(Ledger!$A3="","",Ledger!$E3) | D7: =IF(Ledger!$A3="","",Ledger!$F3) | E7: =IF(Ledger!$A3="","",Ledger!$I3) | F7: =IF(Ledger!$A3="","",COUNTIF(Memo!$C$2:$C$43,Ledger!$A3)) | G7: =IF($A7="","",IF($E7<>"yes","No commentary owed",IF($F7=0,"Owes an explanation, none written","Explained, "&$F7&" sentence(s) on this account")))
A8: =IF(Ledger!$A4="","",Ledger!$A4) | B8: =IF(Ledger!$A4="","",Ledger!$B4) | C8: =IF(Ledger!$A4="","",Ledger!$E4) | D8: =IF(Ledger!$A4="","",Ledger!$F4) | E8: =IF(Ledger!$A4="","",Ledger!$I4) | F8: =IF(Ledger!$A4="","",COUNTIF(Memo!$C$2:$C$43,Ledger!$A4)) | G8: =IF($A8="","",IF($E8<>"yes","No commentary owed",IF($F8=0,"Owes an explanation, none written","Explained, "&$F8&" sentence(s) on this account")))
A9: =IF(Ledger!$A5="","",Ledger!$A5) | B9: =IF(Ledger!$A5="","",Ledger!$B5) | C9: =IF(Ledger!$A5="","",Ledger!$E5) | D9: =IF(Ledger!$A5="","",Ledger!$F5) | E9: =IF(Ledger!$A5="","",Ledger!$I5) | F9: =IF(Ledger!$A5="","",COUNTIF(Memo!$C$2:$C$43,Ledger!$A5)) | G9: =IF($A9="","",IF($E9<>"yes","No commentary owed",IF($F9=0,"Owes an explanation, none written","Explained, "&$F9&" sentence(s) on this account")))
A10: =IF(Ledger!$A6="","",Ledger!$A6) | B10: =IF(Ledger!$A6="","",Ledger!$B6) | C10: =IF(Ledger!$A6="","",Ledger!$E6) | D10: =IF(Ledger!$A6="","",Ledger!$F6) | E10: =IF(Ledger!$A6="","",Ledger!$I6) | F10: =IF(Ledger!$A6="","",COUNTIF(Memo!$C$2:$C$43,Ledger!$A6)) | G10: =IF($A10="","",IF($E10<>"yes","No commentary owed",IF($F10=0,"Owes an explanation, none written","Explained, "&$F10&" sentence(s) on this account")))
A11: =IF(Ledger!$A7="","",Ledger!$A7) | B11: =IF(Ledger!$A7="","",Ledger!$B7) | C11: =IF(Ledger!$A7="","",Ledger!$E7) | D11: =IF(Ledger!$A7="","",Ledger!$F7) | E11: =IF(Ledger!$A7="","",Ledger!$I7) | F11: =IF(Ledger!$A7="","",COUNTIF(Memo!$C$2:$C$43,Ledger!$A7)) | G11: =IF($A11="","",IF($E11<>"yes","No commentary owed",IF($F11=0,"Owes an explanation, none written","Explained, "&$F11&" sentence(s) on this account")))
A12: =IF(Ledger!$A8="","",Ledger!$A8) | B12: =IF(Ledger!$A8="","",Ledger!$B8) | C12: =IF(Ledger!$A8="","",Ledger!$E8) | D12: =IF(Ledger!$A8="","",Ledger!$F8) | E12: =IF(Ledger!$A8="","",Ledger!$I8) | F12: =IF(Ledger!$A8="","",COUNTIF(Memo!$C$2:$C$43,Ledger!$A8)) | G12: =IF($A12="","",IF($E12<>"yes","No commentary owed",IF($F12=0,"Owes an explanation, none written","Explained, "&$F12&" sentence(s) on this account")))
A13: =IF(Ledger!$A9="","",Ledger!$A9) | B13: =IF(Ledger!$A9="","",Ledger!$B9) | C13: =IF(Ledger!$A9="","",Ledger!$E9) | D13: =IF(Ledger!$A9="","",Ledger!$F9) | E13: =IF(Ledger!$A9="","",Ledger!$I9) | F13: =IF(Ledger!$A9="","",COUNTIF(Memo!$C$2:$C$43,Ledger!$A9)) | G13: =IF($A13="","",IF($E13<>"yes","No commentary owed",IF($F13=0,"Owes an explanation, none written","Explained, "&$F13&" sentence(s) on this account")))
A14: =IF(Ledger!$A10="","",Ledger!$A10) | B14: =IF(Ledger!$A10="","",Ledger!$B10) | C14: =IF(Ledger!$A10="","",Ledger!$E10) | D14: =IF(Ledger!$A10="","",Ledger!$F10) | E14: =IF(Ledger!$A10="","",Ledger!$I10) | F14: =IF(Ledger!$A10="","",COUNTIF(Memo!$C$2:$C$43,Ledger!$A10)) | G14: =IF($A14="","",IF($E14<>"yes","No commentary owed",IF($F14=0,"Owes an explanation, none written","Explained, "&$F14&" sentence(s) on this account")))
A15: =IF(Ledger!$A11="","",Ledger!$A11) | B15: =IF(Ledger!$A11="","",Ledger!$B11) | C15: =IF(Ledger!$A11="","",Ledger!$E11) | D15: =IF(Ledger!$A11="","",Ledger!$F11) | E15: =IF(Ledger!$A11="","",Ledger!$I11) | F15: =IF(Ledger!$A11="","",COUNTIF(Memo!$C$2:$C$43,Ledger!$A11)) | G15: =IF($A15="","",IF($E15<>"yes","No commentary owed",IF($F15=0,"Owes an explanation, none written","Explained, "&$F15&" sentence(s) on this account")))
A16: =IF(Ledger!$A12="","",Ledger!$A12) | B16: =IF(Ledger!$A12="","",Ledger!$B12) | C16: =IF(Ledger!$A12="","",Ledger!$E12) | D16: =IF(Ledger!$A12="","",Ledger!$F12) | E16: =IF(Ledger!$A12="","",Ledger!$I12) | F16: =IF(Ledger!$A12="","",COUNTIF(Memo!$C$2:$C$43,Ledger!$A12)) | G16: =IF($A16="","",IF($E16<>"yes","No commentary owed",IF($F16=0,"Owes an explanation, none written","Explained, "&$F16&" sentence(s) on this account")))
A17: =IF(Ledger!$A13="","",Ledger!$A13) | B17: =IF(Ledger!$A13="","",Ledger!$B13) | C17: =IF(Ledger!$A13="","",Ledger!$E13) | D17: =IF(Ledger!$A13="","",Ledger!$F13) | E17: =IF(Ledger!$A13="","",Ledger!$I13) | F17: =IF(Ledger!$A13="","",COUNTIF(Memo!$C$2:$C$43,Ledger!$A13)) | G17: =IF($A17="","",IF($E17<>"yes","No commentary owed",IF($F17=0,"Owes an explanation, none written","Explained, "&$F17&" sentence(s) on this account")))
... A49: =IF(Ledger!$A45="","",Ledger!$A45) | B49: =IF(Ledger!$A45="","",Ledger!$B45) | C49: =IF(Ledger!$A45="","",Ledger!$E45) | D49: =IF(Ledger!$A45="","",Ledger!$F45) | E49: =IF(Ledger!$A45="","",Ledger!$I45) | F49: =IF(Ledger!$A45="","",COUNTIF(Memo!$C$2:$C$43,Ledger!$A45)) | G49: =IF($A49="","",IF($E49<>"yes","No commentary owed",IF($F49=0,"Owes an explanation, none written","Explained, "&$F49&" sentence(s) on this account")))

Sheet Reviewer log
A1: close period | B1: memo version | C1: line | D1: account | E1: sentence | F1: check | G1: result | H1: finding | I1: ask to the controller | J1: reviewer answer | K1: resolved | L1: reviewer name | M1: date | N1: controller sign-off
A2: June 2026, Halyard training case | B2: Draft 2 | C2: 6400 | D2: Bad debt expense | E2: S2 | F2: arithmetic | G2: fail | H2: S2 accounts for $42,000. Account 6400 moved $47,000, from $15,000 to $62,000. The difference is $5,000. | I2: State what the $5,000 above the Coastal Grocers reserve is and produce the June reserve rollforward, or amend S2 to a figure the ledger supports. | J2: Preparer amended S2 to $47,000, which recomputes against the ledger and ties. What the $5,000 above the named Coastal Grocers reserve is has not been established and no June reserve rollforward is on file, so the ask stays open and the sentence is held back from release. | K2: no | L2: K. Alkurd | M2: 2026-07-08 | N2: pending
A3: June 2026, Halyard training case | B3: Draft 2 | C3: 6000 | D3: Warehouse wages | E3: none | F3: silence | G3: fail | H3: The account moved $72,500 and 11.5 percent, which clears both legs, and no sentence in the memo covers it. | I3: Produce a driver for warehouse wages, or confirm the line is released with no explanation and why. | K3: no | L3: K. Alkurd | M3: 2026-07-08 | N3: pending
A4: June 2026, Halyard training case | B4: Draft 2 | C4: 4000 | D4: Product revenue, distribution | E4: S5 | F4: driver | G4: reviewer | H4: S5 credits the $372,000 movement to the Tri-State depot ramp. Nothing in the close binder ties that ramp to the figure, and the pricing memo of 20 May moves freight into the product price from 1 June, which puts $65,000 of the movement in account 4200 rather than in demand. | I4: Produce the support behind the Tri-State ramp, and state how much of the $372,000 is the freight reclassification. | J4: Not supported as written. The $65,000 is a reclassification out of account 4200 under the delivered pricing change, and the rest carries no document. Sentence held back from release. | K4: no | L4: K. Alkurd | M4: 2026-07-08 | N4: pending
